mambajs/__init__.py
mambajs/_version.py
mambajs/cli.py
mambajs/package.json
mambajs/bin/mambajs
mambajs-0.20.1.dist-info/licenses/LICENSE
mambajs-0.20.1.dist-info/METADATA
mambajs-0.20.1.dist-info/WHEEL
mambajs-0.20.1.dist-info/entry_points.txt
mambajs-0.20.1.dist-info/top_level.txt
mambajs-0.20.1.dist-info/RECORD
